threadward/__init__.py
threadward/cli/__init__.py
threadward/cli/init_command.py
threadward/cli/main.py
threadward/core/__init__.py
threadward/core/base.py
threadward/core/interactive.py
threadward/core/task.py
threadward/core/threadward.py
threadward/core/variable_set.py
threadward/core/worker.py
threadward/core/worker_process.py
threadward-0.1.0.dist-info/licenses/LICENSE
threadward-0.1.0.dist-info/METADATA
threadward-0.1.0.dist-info/WHEEL
threadward-0.1.0.dist-info/entry_points.txt
threadward-0.1.0.dist-info/top_level.txt
threadward-0.1.0.dist-info/RECORD
