Metadata-Version: 2.4
Name: threadward
Version: 0.1.0
Summary: Parallel Processing for Generalizable AI Experimentation in Python
Home-page: https://github.com/mamarcus64/threadward
Author: threadward
License: MIT
Project-URL: Homepage, https://github.com/mamarcus64/threadward
Project-URL: Repository, https://github.com/mamarcus64/threadward.git
Classifier: Development Status :: 3 - Alpha
Classifier: Intended Audience :: Developers
Classifier: License :: OSI Approved :: MIT License
Classifier: Operating System :: OS Independent
Classifier: Operating System :: POSIX :: Linux
Classifier: Operating System :: MacOS
Classifier: Operating System :: Microsoft :: Windows
Classifier: Programming Language :: Python :: 3
Classifier: Programming Language :: Python :: 3.8
Classifier: Programming Language :: Python :: 3.9
Classifier: Programming Language :: Python :: 3.10
Classifier: Programming Language :: Python :: 3.11
Requires-Python: >=3.8
License-File: LICENSE
Requires-Dist: psutil>=5.9.0
Requires-Dist: GPUtil>=1.4.0
Dynamic: home-page
Dynamic: license-file
Dynamic: requires-python
